wdlgen/__init__.py
wdlgen/common.py
wdlgen/task.py
wdlgen/types.py
wdlgen/util.py
wdlgen/workflow.py
wdlgen/workflowcall.py
illusional.wdlgen-0.3.1.dist-info/LICENSE
illusional.wdlgen-0.3.1.dist-info/METADATA
illusional.wdlgen-0.3.1.dist-info/WHEEL
illusional.wdlgen-0.3.1.dist-info/top_level.txt
illusional.wdlgen-0.3.1.dist-info/RECORD
