Metadata-Version: 2.1
Name: illusional.wdlgen
Version: 0.3.1
Summary: Contains classes and helpers to generate WDL without worrying about the syntax. This is primarily intended for generating WDL from other in-memory representations of a workflow.
Home-page: https://github.com/PMCC-BioinformaticsCore/python-wdlgen
Author: Richard Lupat
Author-email: richard.lupat@petermac.org
License: GNU
Classifier: Development Status :: 2 - Pre-Alpha
Classifier: Intended Audience :: Developers
Classifier: Topic :: Scientific/Engineering
License-File: LICENSE
